[
  {
    "chunk_id": "sample_pdf_sw_1",
    "text": "1. ) first line here 2. ) second",
    "char_start": 0,
    "char_end": 32,
    "source": "sample_pdf",
    "strategy": "sliding_window",
    "tokens": {
      "BAAI/bge-large-en": 10
    }
  },
  {
    "chunk_id": "sample_pdf_sw_2",
    "text": "here 2. ) second line here pdf title",
    "char_start": 33,
    "char_end": 69,
    "source": "sample_pdf",
    "strategy": "sliding_window",
    "tokens": {
      "BAAI/bge-large-en": 9
    }
  },
  {
    "chunk_id": "sample_pdf_sw_3",
    "text": "line here pdf title",
    "char_start": 70,
    "char_end": 89,
    "source": "sample_pdf",
    "strategy": "sliding_window",
    "tokens": {
      "BAAI/bge-large-en": 4
    }
  }
]